unp.py
unp-0.3.dist-info/DESCRIPTION.rst
unp-0.3.dist-info/entry_points.txt
unp-0.3.dist-info/METADATA
unp-0.3.dist-info/metadata.json
unp-0.3.dist-info/RECORD
unp-0.3.dist-info/top_level.txt
unp-0.3.dist-info/WHEEL
