Metadata-Version: 2.0
Name: unp
Version: 0.3
Summary: Command line tool that can unpack archives easily
Home-page: http://github.com/mitsuhiko/unp
Author: Armin Ronacher
Author-email: armin.ronacher@active-4.com
License: BSD
Platform: UNKNOWN
Classifier: License :: OSI Approved :: BSD License
Classifier: Programming Language :: Python
Requires-Dist: click (>=3.0)
